isl29125.py
circuitpython_isl29125-0.2.3.dist-info/LICENSE
circuitpython_isl29125-0.2.3.dist-info/METADATA
circuitpython_isl29125-0.2.3.dist-info/WHEEL
circuitpython_isl29125-0.2.3.dist-info/top_level.txt
circuitpython_isl29125-0.2.3.dist-info/RECORD
