Metadata-Version: 2.1
Name: circuitpython-isl29125
Version: 0.2.3
Summary: driver for the isl29125 light sensor
Author-email: "Jose D. Montoya" <isl@mailmeto.mozmail.com>
License: MIT
Project-URL: Homepage, https://github.com/jposada202020/CircuitPython_isl29125
Keywords: adafruit,blinka,circuitpython,micropython,isl29125,light,lux,sensor,isl29125,circuitpython,red,green,blue,color
Classifier: Intended Audience :: Developers
Classifier: Topic :: Software Development :: Libraries
Classifier: Topic :: Software Development :: Embedded Systems
Classifier: Topic :: System :: Hardware
Classifier: License :: OSI Approved :: MIT License
Classifier: Programming Language :: Python :: 3
License-File: LICENSE
Requires-Dist: Adafruit-Blinka
Requires-Dist: adafruit-circuitpython-busdevice
Requires-Dist: adafruit-circuitpython-register
Provides-Extra: optional
